{
	"info": {
		"_postman_id": "14d7e3ad-bbcd-45bf-b178-7dbcb3bcfcb7",
		"name": "Health Check Webserver API",
		"schema": "https://schema.getpostman.com/json/collection/v2.1.0/collection.json",
		"_exporter_id": "34385545"
	},
	"item": [
		{
			"name": "Connection Test",
			"request": {
				"method": "GET",
				"header": []
			},
			"response": [
				{
					"name": "Connection Test",
					"originalRequest": {
						"method": "GET",
						"header": [],
						"url": {
							"raw": "http://localhost:5000/",
							"protocol": "http",
							"host": [
								"localhost"
							],
							"port": "5000",
							"path": [
								""
							],
							"query": [
								{
									"key": null,
									"value": null,
									"disabled": true
								}
							]
						}
					},
					"status": "OK",
					"code": 200,
					"_postman_previewlanguage": "json",
					"header": [
						{
							"key": "Server",
							"value": "Werkzeug/3.0.1 Python/3.12.1"
						},
						{
							"key": "Date",
							"value": "Fri, 19 Apr 2024 20:07:14 GMT"
						},
						{
							"key": "Content-Type",
							"value": "application/json"
						},
						{
							"key": "Content-Length",
							"value": "34"
						},
						{
							"key": "Connection",
							"value": "close"
						}
					],
					"cookie": [],
					"body": "\"Database connection successful!\""
				}
			]
		},
		{
			"name": "Get Webservers",
			"request": {
				"method": "GET",
				"header": []
			},
			"response": [
				{
					"name": "Get Webservers",
					"originalRequest": {
						"method": "GET",
						"header": [],
						"url": {
							"raw": "http://localhost:5000/webservers",
							"protocol": "http",
							"host": [
								"localhost"
							],
							"port": "5000",
							"path": [
								"webservers"
							]
						}
					},
					"status": "OK",
					"code": 200,
					"_postman_previewlanguage": "json",
					"header": [
						{
							"key": "Server",
							"value": "Werkzeug/3.0.1 Python/3.12.1"
						},
						{
							"key": "Date",
							"value": "Fri, 19 Apr 2024 20:07:52 GMT"
						},
						{
							"key": "Content-Type",
							"value": "application/json"
						},
						{
							"key": "Content-Length",
							"value": "5"
						},
						{
							"key": "Connection",
							"value": "close"
						}
					],
					"cookie": [],
					"body": "\"[]\""
				}
			]
		},
		{
			"name": "Add a webserver",
			"request": {
				"method": "GET",
				"header": []
			},
			"response": [
				{
					"name": "Add a webserver",
					"originalRequest": {
						"method": "POST",
						"header": [],
						"body": {
							"mode": "raw",
							"raw": "{\"name\": \"Youtube\", \"http_url\": \"https://www.youtube.com/\"}",
							"options": {
								"raw": {
									"language": "json"
								}
							}
						},
						"url": {
							"raw": "http://localhost:5000/webservers",
							"protocol": "http",
							"host": [
								"localhost"
							],
							"port": "5000",
							"path": [
								"webservers"
							]
						}
					},
					"status": "CREATED",
					"code": 201,
					"_postman_previewlanguage": "json",
					"header": [
						{
							"key": "Server",
							"value": "Werkzeug/3.0.1 Python/3.12.1"
						},
						{
							"key": "Date",
							"value": "Fri, 19 Apr 2024 20:08:19 GMT"
						},
						{
							"key": "Content-Type",
							"value": "application/json"
						},
						{
							"key": "Content-Length",
							"value": "71"
						},
						{
							"key": "Connection",
							"value": "close"
						}
					],
					"cookie": [],
					"body": "{\n    \"id\": 1,\n    \"message\": \"Webserver <Youtube> created successfully\"\n}"
				}
			]
		},
		{
			"name": "Get Webservers",
			"request": {
				"method": "GET",
				"header": []
			},
			"response": [
				{
					"name": "Get Webservers",
					"originalRequest": {
						"method": "GET",
						"header": [],
						"url": {
							"raw": "http://localhost:5000/webservers",
							"protocol": "http",
							"host": [
								"localhost"
							],
							"port": "5000",
							"path": [
								"webservers"
							]
						}
					},
					"status": "OK",
					"code": 200,
					"_postman_previewlanguage": "json",
					"header": [
						{
							"key": "Server",
							"value": "Werkzeug/3.0.1 Python/3.12.1"
						},
						{
							"key": "Date",
							"value": "Fri, 19 Apr 2024 20:23:54 GMT"
						},
						{
							"key": "Content-Type",
							"value": "application/json"
						},
						{
							"key": "Content-Length",
							"value": "231"
						},
						{
							"key": "Connection",
							"value": "close"
						}
					],
					"cookie": [],
					"body": "\"[\\n    {\\n        \\\"id\\\": 1,\\n        \\\"info\\\": {\\n            \\\"health\\\": \\\"Healthy\\\",\\n            \\\"http_url\\\": \\\"https://www.youtube.com/\\\",\\n            \\\"name\\\": \\\"Youtube\\\",\\n            \\\"status\\\": 5\\n        }\\n    }\\n]\""
				}
			]
		},
		{
			"name": "DELETE webserver",
			"request": {
				"method": "GET",
				"header": []
			},
			"response": [
				{
					"name": "Youtube deleted",
					"originalRequest": {
						"method": "DELETE",
						"header": [],
						"url": {
							"raw": "http://localhost:5000/webservers/1",
							"protocol": "http",
							"host": [
								"localhost"
							],
							"port": "5000",
							"path": [
								"webservers",
								"1"
							]
						}
					},
					"status": "NO CONTENT",
					"code": 204,
					"_postman_previewlanguage": "json",
					"header": [
						{
							"key": "Server",
							"value": "Werkzeug/3.0.1 Python/3.12.1"
						},
						{
							"key": "Date",
							"value": "Fri, 19 Apr 2024 20:24:14 GMT"
						},
						{
							"key": "Content-Type",
							"value": "application/json"
						},
						{
							"key": "Connection",
							"value": "close"
						}
					],
					"cookie": [],
					"body": null
				}
			]
		},
		{
			"name": "Get Webservers",
			"request": {
				"method": "GET",
				"header": []
			},
			"response": [
				{
					"name": "Empty webservers",
					"originalRequest": {
						"method": "GET",
						"header": [],
						"url": {
							"raw": "http://localhost:5000/webservers",
							"protocol": "http",
							"host": [
								"localhost"
							],
							"port": "5000",
							"path": [
								"webservers"
							]
						}
					},
					"status": "OK",
					"code": 200,
					"_postman_previewlanguage": "json",
					"header": [
						{
							"key": "Server",
							"value": "Werkzeug/3.0.1 Python/3.12.1"
						},
						{
							"key": "Date",
							"value": "Fri, 19 Apr 2024 20:24:41 GMT"
						},
						{
							"key": "Content-Type",
							"value": "application/json"
						},
						{
							"key": "Content-Length",
							"value": "5"
						},
						{
							"key": "Connection",
							"value": "close"
						}
					],
					"cookie": [],
					"body": "\"[]\""
				}
			]
		},
		{
			"name": "Add Webserver",
			"request": {
				"method": "GET",
				"header": []
			},
			"response": [
				{
					"name": "Added Youtube Back",
					"originalRequest": {
						"method": "POST",
						"header": [],
						"body": {
							"mode": "raw",
							"raw": "{\"name\": \"Youtube\", \"http_url\": \"https://www.youtube.com/\"}",
							"options": {
								"raw": {
									"language": "json"
								}
							}
						},
						"url": {
							"raw": "http://localhost:5000/webservers",
							"protocol": "http",
							"host": [
								"localhost"
							],
							"port": "5000",
							"path": [
								"webservers"
							]
						}
					},
					"status": "CREATED",
					"code": 201,
					"_postman_previewlanguage": "json",
					"header": [
						{
							"key": "Server",
							"value": "Werkzeug/3.0.1 Python/3.12.1"
						},
						{
							"key": "Date",
							"value": "Fri, 19 Apr 2024 20:25:51 GMT"
						},
						{
							"key": "Content-Type",
							"value": "application/json"
						},
						{
							"key": "Content-Length",
							"value": "71"
						},
						{
							"key": "Connection",
							"value": "close"
						}
					],
					"cookie": [],
					"body": "{\n    \"id\": 2,\n    \"message\": \"Webserver <Youtube> created successfully\"\n}"
				},
				{
					"name": "Add Google",
					"originalRequest": {
						"method": "POST",
						"header": [
							{
								"key": "Content-Type",
								"name": "Content-Type",
								"value": "application/json",
								"type": "text"
							}
						],
						"body": {
							"mode": "raw",
							"raw": "{\"name\": \"Google\", \"http_url\": \"https://www.google.com/\"}",
							"options": {
								"raw": {
									"language": "json"
								}
							}
						},
						"url": {
							"raw": "http://localhost:5000/webservers",
							"protocol": "http",
							"host": [
								"localhost"
							],
							"port": "5000",
							"path": [
								"webservers"
							]
						}
					},
					"status": "CREATED",
					"code": 201,
					"_postman_previewlanguage": "json",
					"header": [
						{
							"key": "Server",
							"value": "Werkzeug/3.0.1 Python/3.12.1"
						},
						{
							"key": "Date",
							"value": "Fri, 19 Apr 2024 20:26:17 GMT"
						},
						{
							"key": "Content-Type",
							"value": "application/json"
						},
						{
							"key": "Content-Length",
							"value": "70"
						},
						{
							"key": "Connection",
							"value": "close"
						}
					],
					"cookie": [],
					"body": "{\n    \"id\": 3,\n    \"message\": \"Webserver <Google> created successfully\"\n}"
				}
			]
		},
		{
			"name": "Get Webservers",
			"request": {
				"method": "GET",
				"header": []
			},
			"response": [
				{
					"name": "Shows All",
					"originalRequest": {
						"method": "GET",
						"header": [],
						"url": {
							"raw": "http://localhost:5000/webservers",
							"protocol": "http",
							"host": [
								"localhost"
							],
							"port": "5000",
							"path": [
								"webservers"
							]
						}
					},
					"status": "OK",
					"code": 200,
					"_postman_previewlanguage": "json",
					"header": [
						{
							"key": "Server",
							"value": "Werkzeug/3.0.1 Python/3.12.1"
						},
						{
							"key": "Date",
							"value": "Fri, 19 Apr 2024 20:26:48 GMT"
						},
						{
							"key": "Content-Type",
							"value": "application/json"
						},
						{
							"key": "Content-Length",
							"value": "454"
						},
						{
							"key": "Connection",
							"value": "close"
						}
					],
					"cookie": [],
					"body": "\"[\\n    {\\n        \\\"id\\\": 2,\\n        \\\"info\\\": {\\n            \\\"health\\\": \\\"Healthy\\\",\\n            \\\"http_url\\\": \\\"https://www.youtube.com/\\\",\\n            \\\"name\\\": \\\"Youtube\\\",\\n            \\\"status\\\": 5\\n        }\\n    },\\n    {\\n        \\\"id\\\": 3,\\n        \\\"info\\\": {\\n            \\\"health\\\": \\\"Healthy\\\",\\n            \\\"http_url\\\": \\\"https://www.google.com/\\\",\\n            \\\"name\\\": \\\"Google\\\",\\n            \\\"status\\\": 5\\n        }\\n    }\\n]\""
				}
			]
		},
		{
			"name": "Add Webserver With Invalid  URL",
			"request": {
				"method": "GET",
				"header": []
			},
			"response": [
				{
					"name": "Webserver Added",
					"originalRequest": {
						"method": "POST",
						"header": [],
						"body": {
							"mode": "raw",
							"raw": "{\"name\": \"Orel\", \"http_url\": \"https://orelzamler.com/\"}",
							"options": {
								"raw": {
									"language": "json"
								}
							}
						},
						"url": {
							"raw": "http://localhost:5000/webservers",
							"protocol": "http",
							"host": [
								"localhost"
							],
							"port": "5000",
							"path": [
								"webservers"
							]
						}
					},
					"status": "CREATED",
					"code": 201,
					"_postman_previewlanguage": "json",
					"header": [
						{
							"key": "Server",
							"value": "Werkzeug/3.0.1 Python/3.12.1"
						},
						{
							"key": "Date",
							"value": "Fri, 19 Apr 2024 20:27:25 GMT"
						},
						{
							"key": "Content-Type",
							"value": "application/json"
						},
						{
							"key": "Content-Length",
							"value": "68"
						},
						{
							"key": "Connection",
							"value": "close"
						}
					],
					"cookie": [],
					"body": "{\n    \"id\": 4,\n    \"message\": \"Webserver <Orel> created successfully\"\n}"
				}
			]
		},
		{
			"name": "Get Valid URL history",
			"request": {
				"method": "GET",
				"header": []
			},
			"response": [
				{
					"name": "Googles History",
					"originalRequest": {
						"method": "GET",
						"header": [],
						"url": {
							"raw": "http://localhost:5000/webservers/3",
							"protocol": "http",
							"host": [
								"localhost"
							],
							"port": "5000",
							"path": [
								"webservers",
								"3"
							]
						}
					},
					"status": "OK",
					"code": 200,
					"_postman_previewlanguage": "json",
					"header": [
						{
							"key": "Server",
							"value": "Werkzeug/3.0.1 Python/3.12.1"
						},
						{
							"key": "Date",
							"value": "Fri, 19 Apr 2024 20:28:11 GMT"
						},
						{
							"key": "Content-Type",
							"value": "application/json"
						},
						{
							"key": "Content-Length",
							"value": "2635"
						},
						{
							"key": "Connection",
							"value": "close"
						}
					],
					"cookie": [],
					"body": "\"{\\n    \\\"last_10_requests\\\": [\\n        {\\n            \\\"request_1\\\": {\\n                \\\"latency\\\": 1.13457,\\n                \\\"response_code\\\": 200,\\n                \\\"timestamp\\\": \\\"2024-04-19 20:28:08\\\",\\n                \\\"webserver_id\\\": 3\\n            }\\n        },\\n        {\\n            \\\"request_2\\\": {\\n                \\\"latency\\\": 1.02113,\\n                \\\"response_code\\\": 200,\\n                \\\"timestamp\\\": \\\"2024-04-19 20:28:02\\\",\\n                \\\"webserver_id\\\": 3\\n            }\\n        },\\n        {\\n            \\\"request_3\\\": {\\n                \\\"latency\\\": 1.13689,\\n                \\\"response_code\\\": 200,\\n                \\\"timestamp\\\": \\\"2024-04-19 20:27:56\\\",\\n                \\\"webserver_id\\\": 3\\n            }\\n        },\\n        {\\n            \\\"request_4\\\": {\\n                \\\"latency\\\": 1.08191,\\n                \\\"response_code\\\": 200,\\n                \\\"timestamp\\\": \\\"2024-04-19 20:27:50\\\",\\n                \\\"webserver_id\\\": 3\\n            }\\n        },\\n        {\\n            \\\"request_5\\\": {\\n                \\\"latency\\\": 1.11645,\\n                \\\"response_code\\\": 200,\\n                \\\"timestamp\\\": \\\"2024-04-19 20:27:44\\\",\\n                \\\"webserver_id\\\": 3\\n            }\\n        },\\n        {\\n            \\\"request_6\\\": {\\n                \\\"latency\\\": 1.04975,\\n                \\\"response_code\\\": 200,\\n                \\\"timestamp\\\": \\\"2024-04-19 20:27:38\\\",\\n                \\\"webserver_id\\\": 3\\n            }\\n        },\\n        {\\n            \\\"request_7\\\": {\\n                \\\"latency\\\": 1.17796,\\n                \\\"response_code\\\": 200,\\n                \\\"timestamp\\\": \\\"2024-04-19 20:27:32\\\",\\n                \\\"webserver_id\\\": 3\\n            }\\n        },\\n        {\\n            \\\"request_8\\\": {\\n                \\\"latency\\\": 1.26002,\\n                \\\"response_code\\\": 200,\\n                \\\"timestamp\\\": \\\"2024-04-19 20:27:26\\\",\\n                \\\"webserver_id\\\": 3\\n            }\\n        },\\n        {\\n            \\\"request_9\\\": {\\n                \\\"latency\\\": 1.13992,\\n                \\\"response_code\\\": 200,\\n                \\\"timestamp\\\": \\\"2024-04-19 20:27:20\\\",\\n                \\\"webserver_id\\\": 3\\n            }\\n        },\\n        {\\n            \\\"request_10\\\": {\\n                \\\"latency\\\": 1.13449,\\n                \\\"response_code\\\": 200,\\n                \\\"timestamp\\\": \\\"2024-04-19 20:27:14\\\",\\n                \\\"webserver_id\\\": 3\\n            }\\n        }\\n    ],\\n    \\\"server_info\\\": {\\n        \\\"health\\\": \\\"Healthy\\\",\\n        \\\"http_url\\\": \\\"https://www.google.com/\\\",\\n        \\\"name\\\": \\\"Google\\\",\\n        \\\"status\\\": 5\\n    }\\n}\""
				}
			]
		},
		{
			"name": "Get Invalid URL History",
			"request": {
				"method": "GET",
				"header": []
			},
			"response": [
				{
					"name": "Orelzam History",
					"originalRequest": {
						"method": "GET",
						"header": [],
						"url": {
							"raw": "http://localhost:5000/webservers/4",
							"protocol": "http",
							"host": [
								"localhost"
							],
							"port": "5000",
							"path": [
								"webservers",
								"4"
							]
						}
					},
					"status": "OK",
					"code": 200,
					"_postman_previewlanguage": "json",
					"header": [
						{
							"key": "Server",
							"value": "Werkzeug/3.0.1 Python/3.12.1"
						},
						{
							"key": "Date",
							"value": "Fri, 19 Apr 2024 20:28:48 GMT"
						},
						{
							"key": "Content-Type",
							"value": "application/json"
						},
						{
							"key": "Content-Length",
							"value": "208"
						},
						{
							"key": "Connection",
							"value": "close"
						}
					],
					"cookie": [],
					"body": "\"{\\n    \\\"last_10_requests\\\": [],\\n    \\\"server_info\\\": {\\n        \\\"health\\\": \\\"Unstable\\\",\\n        \\\"http_url\\\": \\\"https://orelzamler.com/\\\",\\n        \\\"name\\\": \\\"Orel\\\",\\n        \\\"status\\\": 0\\n    }\\n}\""
				}
			]
		},
		{
			"name": "GET Specific Webserver",
			"request": {
				"method": "GET",
				"header": []
			},
			"response": [
				{
					"name": "10 Last Request & Webserver Info",
					"originalRequest": {
						"method": "GET",
						"header": [],
						"url": {
							"raw": "http://localhost:5000/webservers/3",
							"protocol": "http",
							"host": [
								"localhost"
							],
							"port": "5000",
							"path": [
								"webservers",
								"3"
							]
						}
					},
					"status": "OK",
					"code": 200,
					"_postman_previewlanguage": "json",
					"header": [
						{
							"key": "Server",
							"value": "Werkzeug/3.0.1 Python/3.12.1"
						},
						{
							"key": "Date",
							"value": "Fri, 19 Apr 2024 20:29:18 GMT"
						},
						{
							"key": "Content-Type",
							"value": "application/json"
						},
						{
							"key": "Content-Length",
							"value": "2635"
						},
						{
							"key": "Connection",
							"value": "close"
						}
					],
					"cookie": [],
					"body": "\"{\\n    \\\"last_10_requests\\\": [\\n        {\\n            \\\"request_1\\\": {\\n                \\\"latency\\\": 1.14048,\\n                \\\"response_code\\\": 200,\\n                \\\"timestamp\\\": \\\"2024-04-19 20:29:14\\\",\\n                \\\"webserver_id\\\": 3\\n            }\\n        },\\n        {\\n            \\\"request_2\\\": {\\n                \\\"latency\\\": 1.12558,\\n                \\\"response_code\\\": 200,\\n                \\\"timestamp\\\": \\\"2024-04-19 20:29:08\\\",\\n                \\\"webserver_id\\\": 3\\n            }\\n        },\\n        {\\n            \\\"request_3\\\": {\\n                \\\"latency\\\": 1.21097,\\n                \\\"response_code\\\": 200,\\n                \\\"timestamp\\\": \\\"2024-04-19 20:29:02\\\",\\n                \\\"webserver_id\\\": 3\\n            }\\n        },\\n        {\\n            \\\"request_4\\\": {\\n                \\\"latency\\\": 1.03914,\\n                \\\"response_code\\\": 200,\\n                \\\"timestamp\\\": \\\"2024-04-19 20:28:56\\\",\\n                \\\"webserver_id\\\": 3\\n            }\\n        },\\n        {\\n            \\\"request_5\\\": {\\n                \\\"latency\\\": 1.21595,\\n                \\\"response_code\\\": 200,\\n                \\\"timestamp\\\": \\\"2024-04-19 20:28:50\\\",\\n                \\\"webserver_id\\\": 3\\n            }\\n        },\\n        {\\n            \\\"request_6\\\": {\\n                \\\"latency\\\": 1.83476,\\n                \\\"response_code\\\": 200,\\n                \\\"timestamp\\\": \\\"2024-04-19 20:28:45\\\",\\n                \\\"webserver_id\\\": 3\\n            }\\n        },\\n        {\\n            \\\"request_7\\\": {\\n                \\\"latency\\\": 1.22255,\\n                \\\"response_code\\\": 200,\\n                \\\"timestamp\\\": \\\"2024-04-19 20:28:38\\\",\\n                \\\"webserver_id\\\": 3\\n            }\\n        },\\n        {\\n            \\\"request_8\\\": {\\n                \\\"latency\\\": 1.09347,\\n                \\\"response_code\\\": 200,\\n                \\\"timestamp\\\": \\\"2024-04-19 20:28:32\\\",\\n                \\\"webserver_id\\\": 3\\n            }\\n        },\\n        {\\n            \\\"request_9\\\": {\\n                \\\"latency\\\": 1.14483,\\n                \\\"response_code\\\": 200,\\n                \\\"timestamp\\\": \\\"2024-04-19 20:28:26\\\",\\n                \\\"webserver_id\\\": 3\\n            }\\n        },\\n        {\\n            \\\"request_10\\\": {\\n                \\\"latency\\\": 1.07089,\\n                \\\"response_code\\\": 200,\\n                \\\"timestamp\\\": \\\"2024-04-19 20:28:20\\\",\\n                \\\"webserver_id\\\": 3\\n            }\\n        }\\n    ],\\n    \\\"server_info\\\": {\\n        \\\"health\\\": \\\"Healthy\\\",\\n        \\\"http_url\\\": \\\"https://www.google.com/\\\",\\n        \\\"name\\\": \\\"Google\\\",\\n        \\\"status\\\": 5\\n    }\\n}\""
				},
				{
					"name": "Invalid Has Info But Not History",
					"originalRequest": {
						"method": "GET",
						"header": [
							{
								"key": "Content-Type",
								"name": "Content-Type",
								"value": "application/json",
								"type": "text"
							}
						],
						"body": {
							"mode": "raw",
							"raw": "{\"name\": \"Test\"}",
							"options": {
								"raw": {
									"language": "json"
								}
							}
						},
						"url": {
							"raw": "http://localhost:5000/webservers/4",
							"protocol": "http",
							"host": [
								"localhost"
							],
							"port": "5000",
							"path": [
								"webservers",
								"4"
							]
						}
					},
					"status": "OK",
					"code": 200,
					"_postman_previewlanguage": "json",
					"header": [
						{
							"key": "Server",
							"value": "Werkzeug/3.0.1 Python/3.12.1"
						},
						{
							"key": "Date",
							"value": "Fri, 19 Apr 2024 20:29:50 GMT"
						},
						{
							"key": "Content-Type",
							"value": "application/json"
						},
						{
							"key": "Content-Length",
							"value": "208"
						},
						{
							"key": "Connection",
							"value": "close"
						}
					],
					"cookie": [],
					"body": "\"{\\n    \\\"last_10_requests\\\": [],\\n    \\\"server_info\\\": {\\n        \\\"health\\\": \\\"Unstable\\\",\\n        \\\"http_url\\\": \\\"https://orelzamler.com/\\\",\\n        \\\"name\\\": \\\"Orel\\\",\\n        \\\"status\\\": 0\\n    }\\n}\""
				}
			]
		},
		{
			"name": "UPDATE Name",
			"request": {
				"method": "PUT",
				"header": [],
				"body": {
					"mode": "raw",
					"raw": "{\"name\": \"Test\"}",
					"options": {
						"raw": {
							"language": "json"
						}
					}
				},
				"url": {
					"raw": "http://localhost:5000/webservers/4",
					"protocol": "http",
					"host": [
						"localhost"
					],
					"port": "5000",
					"path": [
						"webservers",
						"4"
					]
				}
			},
			"response": [
				{
					"name": "Name Changed",
					"originalRequest": {
						"method": "PUT",
						"header": [],
						"body": {
							"mode": "raw",
							"raw": "{\"name\": \"Test\"}",
							"options": {
								"raw": {
									"language": "json"
								}
							}
						},
						"url": {
							"raw": "http://localhost:5000/webservers/4",
							"protocol": "http",
							"host": [
								"localhost"
							],
							"port": "5000",
							"path": [
								"webservers",
								"4"
							]
						}
					},
					"status": "CREATED",
					"code": 201,
					"_postman_previewlanguage": "json",
					"header": [
						{
							"key": "Server",
							"value": "Werkzeug/3.0.1 Python/3.12.1"
						},
						{
							"key": "Date",
							"value": "Fri, 19 Apr 2024 20:30:34 GMT"
						},
						{
							"key": "Content-Type",
							"value": "application/json"
						},
						{
							"key": "Content-Length",
							"value": "55"
						},
						{
							"key": "Connection",
							"value": "close"
						}
					],
					"cookie": [],
					"body": "{\n    \"message\": \"Webserver Test updated successfully\"\n}"
				},
				{
					"name": "Changed Invalid URL To Valid",
					"originalRequest": {
						"method": "PUT",
						"header": [],
						"body": {
							"mode": "raw",
							"raw": "{\"http_url\": \"https://facebook.com/\"}",
							"options": {
								"raw": {
									"language": "json"
								}
							}
						},
						"url": {
							"raw": "http://localhost:5000/webservers/4",
							"protocol": "http",
							"host": [
								"localhost"
							],
							"port": "5000",
							"path": [
								"webservers",
								"4"
							]
						}
					},
					"status": "CREATED",
					"code": 201,
					"_postman_previewlanguage": "json",
					"header": [
						{
							"key": "Server",
							"value": "Werkzeug/3.0.1 Python/3.12.1"
						},
						{
							"key": "Date",
							"value": "Fri, 19 Apr 2024 20:31:16 GMT"
						},
						{
							"key": "Content-Type",
							"value": "application/json"
						},
						{
							"key": "Content-Length",
							"value": "55"
						},
						{
							"key": "Connection",
							"value": "close"
						}
					],
					"cookie": [],
					"body": "{\n    \"message\": \"Webserver Test updated successfully\"\n}"
				}
			]
		},
		{
			"name": "Get webservers",
			"request": {
				"method": "GET",
				"header": []
			},
			"response": [
				{
					"name": "Now His Status Is Healty",
					"originalRequest": {
						"method": "GET",
						"header": [],
						"url": {
							"raw": "http://localhost:5000/webservers",
							"protocol": "http",
							"host": [
								"localhost"
							],
							"port": "5000",
							"path": [
								"webservers"
							]
						}
					},
					"status": "OK",
					"code": 200,
					"_postman_previewlanguage": "json",
					"header": [
						{
							"key": "Server",
							"value": "Werkzeug/3.0.1 Python/3.12.1"
						},
						{
							"key": "Date",
							"value": "Fri, 19 Apr 2024 20:31:40 GMT"
						},
						{
							"key": "Content-Type",
							"value": "application/json"
						},
						{
							"key": "Content-Length",
							"value": "673"
						},
						{
							"key": "Connection",
							"value": "close"
						}
					],
					"cookie": [],
					"body": "\"[\\n    {\\n        \\\"id\\\": 2,\\n        \\\"info\\\": {\\n            \\\"health\\\": \\\"Healthy\\\",\\n            \\\"http_url\\\": \\\"https://www.youtube.com/\\\",\\n            \\\"name\\\": \\\"Youtube\\\",\\n            \\\"status\\\": 5\\n        }\\n    },\\n    {\\n        \\\"id\\\": 3,\\n        \\\"info\\\": {\\n            \\\"health\\\": \\\"Healthy\\\",\\n            \\\"http_url\\\": \\\"https://www.google.com/\\\",\\n            \\\"name\\\": \\\"Google\\\",\\n            \\\"status\\\": 5\\n        }\\n    },\\n    {\\n        \\\"id\\\": 4,\\n        \\\"info\\\": {\\n            \\\"health\\\": \\\"Healthy\\\",\\n            \\\"http_url\\\": \\\"https://facebook.com/\\\",\\n            \\\"name\\\": \\\"Test\\\",\\n            \\\"status\\\": 5\\n        }\\n    }\\n]\""
				}
			]
		},
		{
			"name": "Request Dosnt Exist",
			"request": {
				"method": "GET",
				"header": []
			},
			"response": [
				{
					"name": "Error Handled And Displayed",
					"originalRequest": {
						"method": "GET",
						"header": [],
						"url": {
							"raw": "http://localhost:5000/doesntexist",
							"protocol": "http",
							"host": [
								"localhost"
							],
							"port": "5000",
							"path": [
								"doesntexist"
							]
						}
					},
					"status": "NOT FOUND",
					"code": 404,
					"_postman_previewlanguage": "html",
					"header": [
						{
							"key": "Server",
							"value": "Werkzeug/3.0.1 Python/3.12.1"
						},
						{
							"key": "Date",
							"value": "Fri, 19 Apr 2024 20:34:08 GMT"
						},
						{
							"key": "Content-Type",
							"value": "text/html; charset=utf-8"
						},
						{
							"key": "Content-Length",
							"value": "207"
						},
						{
							"key": "Connection",
							"value": "close"
						}
					],
					"cookie": [],
					"body": "<!doctype html><html lang=en><title>404 Not Found</title><h1>Not Found</h1><p>The requested URL was not found on the server. If you entered the URL manually please check your spelling and try again.</p>"
				}
			]
		}
	]
}